[
    {
        "artist": "姚晓棠",
        "videos": [
            {
                "video_id": "ULYksmjBwzY",
                "title": "最后一页",
                "upload_date": "2024-04-26T13:59:34Z",
                "views": 41679980,
                "comments": 1450,
                "likes": 85179,
                "duration": "PT4M35S"
            },
            {
                "video_id": "376utoTabMI",
                "title": "看着我的眼睛说",
                "upload_date": "2025-05-30T14:00:05Z",
                "views": 26070799,
                "comments": 2295,
                "likes": 87668,
                "duration": "PT4M37S"
            },
            {
                "video_id": "b0nv-NZj2fE",
                "title": "最后一页",
                "upload_date": "2024-05-07T14:51:34Z",
                "views": 15319817,
                "comments": 0,
                "likes": 42028,
                "duration": "PT3M44S"
            },
            {
                "video_id": "o0TyNAdsKZ8",
                "title": "妥协",
                "upload_date": "2024-06-14T14:36:05Z",
                "views": 14441722,
                "comments": 457,
                "likes": 27584,
                "duration": "PT4M2S"
            },
            {
                "video_id": "O3if3wCqh_w",
                "title": "座位",
                "upload_date": "2025-04-25T14:00:39Z",
                "views": 13372954,
                "comments": 903,
                "likes": 37640,
                "duration": "PT3M36S"
            },
            {
                "video_id": "FW_6AVvtHFQ",
                "title": "虹之间",
                "upload_date": "2024-05-17T14:20:28Z",
                "views": 10561024,
                "comments": 244,
                "likes": 17460,
                "duration": "PT3M24S"
            },
            {
                "video_id": "uwY63fqyBSs",
                "title": "错的人",
                "upload_date": "2024-06-28T14:31:36Z",
                "views": 10090461,
                "comments": 1089,
                "likes": 22835,
                "duration": "PT4M54S"
            },
            {
                "video_id": "BLiUN9AxJWI",
                "title": "看着我的眼睛说",
                "upload_date": "2025-05-30T16:41:00Z",
                "views": 9965882,
                "comments": 0,
                "likes": 28873,
                "duration": "PT4M41S"
            },
            {
                "video_id": "iwOE4f2x2AU",
                "title": "我会好好的",
                "upload_date": "2024-05-03T14:54:51Z",
                "views": 9774313,
                "comments": 1023,
                "likes": 20449,
                "duration": "PT4M39S"
            },
            {
                "video_id": "MpgP2aFXdfs",
                "title": "会开花的云",
                "upload_date": "2024-07-05T15:54:05Z",
                "views": 8898258,
                "comments": 450,
                "likes": 24741,
                "duration": "PT4M"
            }
        ],
        "total_views": 160175210,
        "total_comments": 7911,
        "total_likes": 394457,
        "total_results_num": 110662,
        "day_trend": 2934213,
        "week_trend": 4711558,
        "month_trend": 11454138
    },
    {
        "artist": "单依纯",
        "videos": [
            {
                "video_id": "bG563p_moiE",
                "title": "愛我的時候",
                "upload_date": "2021-05-18T12:00:30Z",
                "views": 36400709,
                "comments": 2053,
                "likes": 106972,
                "duration": "PT3M43S"
            },
            {
                "video_id": "40iCGaUhTbE",
                "title": "如果爱忘了",
                "upload_date": "2024-02-17T07:45:00Z",
                "views": 25591230,
                "comments": 1381,
                "likes": 68958,
                "duration": "PT3M45S"
            },
            {
                "video_id": "fqBbnUZbQjc",
                "title": "如果爱忘了",
                "upload_date": "2024-02-22T12:00:37Z",
                "views": 21505380,
                "comments": 585,
                "likes": 59243,
                "duration": "PT4M4S"
            },
            {
                "video_id": "UQjN0cS_Mno",
                "title": "下雨天",
                "upload_date": "2021-02-07T07:28:41Z",
                "views": 19078734,
                "comments": 2515,
                "likes": 59478,
                "duration": "PT4M36S"
            },
            {
                "video_id": "SRy1qDusFoU",
                "title": "你就不要想起我",
                "upload_date": "2021-02-14T14:03:45Z",
                "views": 16648688,
                "comments": 2009,
                "likes": 64367,
                "duration": "PT4M26S"
            },
            {
                "video_id": "1YCqSoZHBK8",
                "title": "如果愛忘了",
                "upload_date": "2024-03-19T04:57:21Z",
                "views": 13487801,
                "comments": 419,
                "likes": 44205,
                "duration": "PT4M6S"
            },
            {
                "video_id": "c85lPOGqq98",
                "title": "想你时风起",
                "upload_date": "2023-07-16T10:04:39Z",
                "views": 11888762,
                "comments": 126,
                "likes": 33677,
                "duration": "PT4M37S"
            },
            {
                "video_id": "WZ82g3G7w_M",
                "title": "如果愛忘了",
                "upload_date": "2024-02-21T11:30:13Z",
                "views": 11334048,
                "comments": 177,
                "likes": 29034,
                "duration": "PT4M6S"
            },
            {
                "video_id": "ptkBKBm4y_4",
                "title": "这么近 那么远",
                "upload_date": "2022-06-12T07:33:24Z",
                "views": 9994471,
                "comments": 2378,
                "likes": 28641,
                "duration": "PT5M41S"
            },
            {
                "video_id": "6mspfiZHpUI",
                "title": "爱与痛的边缘",
                "upload_date": "2022-04-24T11:35:17Z",
                "views": 8578527,
                "comments": 3520,
                "likes": 30525,
                "duration": "PT4M34S"
            }
        ],
        "total_views": 174508350,
        "total_comments": 15163,
        "total_likes": 525100,
        "total_results_num": 873879,
        "day_trend": 9104105,
        "week_trend": 9748241,
        "month_trend": 16633523
    },
    {
        "artist": "黄子弘凡",
        "videos": [
            {
                "video_id": "UjPVe-9awKM",
                "title": "一起走过的日子",
                "upload_date": "2024-12-06T08:41:12Z",
                "views": 3911608,
                "comments": 264,
                "likes": 8170,
                "duration": "PT3M39S"
            },
            {
                "video_id": "LlHH0KUVyFQ",
                "title": "Doppler Longings",
                "upload_date": "2025-10-29T13:00:07Z",
                "views": 3871680,
                "comments": 282,
                "likes": 2683,
                "duration": "PT5M14S"
            },
            {
                "video_id": "cUfFrcbcSmU",
                "title": "Grow up",
                "upload_date": "2025-10-17T13:00:07Z",
                "views": 3611116,
                "comments": 654,
                "likes": 8059,
                "duration": "PT4M48S"
            },
            {
                "video_id": "Pm8yUFsPlvU",
                "title": "忘了没有",
                "upload_date": "2025-04-25T14:00:41Z",
                "views": 3369875,
                "comments": 129,
                "likes": 4838,
                "duration": "PT4M31S"
            },
            {
                "video_id": "HlF98qLYywg",
                "title": "只为你着迷",
                "upload_date": "2025-05-02T14:00:20Z",
                "views": 2338205,
                "comments": 150,
                "likes": 7207,
                "duration": "PT4M35S"
            },
            {
                "video_id": "OdvQFZT8TMg",
                "title": "一点",
                "upload_date": "2025-05-16T14:30:24Z",
                "views": 2148443,
                "comments": 175,
                "likes": 11503,
                "duration": "PT3M47S"
            },
            {
                "video_id": "DMZGQIOXFmE",
                "title": "忘了",
                "upload_date": "2025-06-06T14:00:27Z",
                "views": 2137251,
                "comments": 171,
                "likes": 5864,
                "duration": "PT3M26S"
            },
            {
                "video_id": "uDx_vztO8AM",
                "title": "转身即心痛",
                "upload_date": "2025-04-18T14:04:50Z",
                "views": 2116755,
                "comments": 227,
                "likes": 8279,
                "duration": "PT3M38S"
            },
            {
                "video_id": "pTbeaorZInQ",
                "title": "无赖",
                "upload_date": "2025-01-08T07:11:29Z",
                "views": 1453840,
                "comments": 125,
                "likes": 3299,
                "duration": "PT4M30S"
            },
            {
                "video_id": "NAxkF2m2XSM",
                "title": "忘了",
                "upload_date": "2025-06-07T12:20:04Z",
                "views": 1035517,
                "comments": 0,
                "likes": 2422,
                "duration": "PT3M26S"
            }
        ],
        "total_views": 25994290,
        "total_comments": 2177,
        "total_likes": 62324,
        "total_results_num": 115583,
        "day_trend": 429830,
        "week_trend": 684414,
        "month_trend": 5892472
    },
    {
        "artist": "希林娜依高",
        "videos": [
            {
                "video_id": "YtkgUVGm_n8",
                "title": "慢冷",
                "upload_date": "2023-04-28T15:21:34Z",
                "views": 16939545,
                "comments": 707,
                "likes": 33204,
                "duration": "PT5M8S"
            },
            {
                "video_id": "sBOxUImZFyQ",
                "title": "希林小烟嗓绝了",
                "upload_date": "2020-05-03T17:58:09Z",
                "views": 14864016,
                "comments": 5090,
                "likes": 381479,
                "duration": "PT1M49S"
            },
            {
                "video_id": "OLQnOAalYag",
                "title": "BABYDOLL",
                "upload_date": "2022-08-18T16:00:15Z",
                "views": 10180489,
                "comments": 1668,
                "likes": 152764,
                "duration": "PT2M37S"
            },
            {
                "video_id": "093JOWo1vqE",
                "title": "她来听我的演唱会",
                "upload_date": "2017-09-15T14:30:07Z",
                "views": 9612563,
                "comments": 1213,
                "likes": 32354,
                "duration": "PT4M43S"
            },
            {
                "video_id": "IAWVOxtIuGA",
                "title": "天若有情",
                "upload_date": "2024-05-10T14:45:44Z",
                "views": 7618104,
                "comments": 249,
                "likes": 16107,
                "duration": "PT4M10S"
            },
            {
                "video_id": "r90-f0677xA",
                "title": "男孩",
                "upload_date": "2017-09-18T16:58:52Z",
                "views": 7253790,
                "comments": 763,
                "likes": 24374,
                "duration": "PT4M34S"
            },
            {
                "video_id": "ld8aaSWAnmc",
                "title": "I Like You",
                "upload_date": "2020-05-03T18:12:05Z",
                "views": 5904264,
                "comments": 2174,
                "likes": 116756,
                "duration": "PT1M57S"
            },
            {
                "video_id": "F0sdSKEafao",
                "title": "Someone You Loved",
                "upload_date": "2020-05-08T10:31:53Z",
                "views": 4569411,
                "comments": 747,
                "likes": 98778,
                "duration": "PT1M16S"
            },
            {
                "video_id": "yVP9jSJtITM",
                "title": "她来听我的演唱会",
                "upload_date": "2017-09-18T16:58:27Z",
                "views": 4485186,
                "comments": 429,
                "likes": 18291,
                "duration": "PT4M41S"
            },
            {
                "video_id": "Kv35G7r-Cxg",
                "title": "怎么会忘记你",
                "upload_date": "2023-06-02T14:28:46Z",
                "views": 4007495,
                "comments": 189,
                "likes": 10420,
                "duration": "PT4M23S"
            }
        ],
        "total_views": 85434863,
        "total_comments": 13229,
        "total_likes": 884527,
        "total_results_num": 171393,
        "day_trend": 161023,
        "week_trend": 262443,
        "month_trend": 3167493
    },
    {
        "artist": "毛不易",
        "videos": [
            {
                "video_id": "dDV36GmFP20",
                "title": "不染",
                "upload_date": "2018-04-16T08:59:23Z",
                "views": 33672171,
                "comments": 3127,
                "likes": 96918,
                "duration": "PT5M26S"
            },
            {
                "video_id": "G306LT0p9FY",
                "title": "不染",
                "upload_date": "2018-03-26T11:32:43Z",
                "views": 18727155,
                "comments": 1288,
                "likes": 61908,
                "duration": "PT5M27S"
            },
            {
                "video_id": "EZxVmhM6UpE",
                "title": "突然好想你",
                "upload_date": "2020-05-31T14:26:23Z",
                "views": 17014960,
                "comments": 1785,
                "likes": 86967,
                "duration": "PT4M34S"
            },
            {
                "video_id": "vqbh0h6kquQ",
                "title": "不染",
                "upload_date": "2019-10-05T06:41:48Z",
                "views": 12622093,
                "comments": 140,
                "likes": 43507,
                "duration": "PT5M26S"
            },
            {
                "video_id": "JYtK8sLOh2Y",
                "title": "梅香如故",
                "upload_date": "2018-08-24T04:30:02Z",
                "views": 9548214,
                "comments": 667,
                "likes": 27598,
                "duration": "PT4M3S"
            },
            {
                "video_id": "54AN2Ikljfo",
                "title": "消愁",
                "upload_date": "2023-11-28T01:26:50Z",
                "views": 7805585,
                "comments": 0,
                "likes": 20690,
                "duration": "PT4M22S"
            },
            {
                "video_id": "9C3Nd5dRin8",
                "title": "消愁",
                "upload_date": "2023-12-01T06:02:57Z",
                "views": 7071260,
                "comments": 532,
                "likes": 20992,
                "duration": "PT4M22S"
            },
            {
                "video_id": "_SUwUaP14Gs",
                "title": "像我这样的人",
                "upload_date": "2018-12-21T14:45:14Z",
                "views": 6699985,
                "comments": 2581,
                "likes": 25573,
                "duration": "PT5M20S"
            },
            {
                "video_id": "0r1ct8L_i_A",
                "title": "给你给我",
                "upload_date": "2021-09-24T04:30:01Z",
                "views": 6560786,
                "comments": 736,
                "likes": 32775,
                "duration": "PT4M5S"
            },
            {
                "video_id": "peKyk89tnlM",
                "title": "無名的人",
                "upload_date": "2024-02-22T11:30:22Z",
                "views": 6319525,
                "comments": 444,
                "likes": 22414,
                "duration": "PT4M43S"
            }
        ],
        "total_views": 126041734,
        "total_comments": 11300,
        "total_likes": 439342,
        "total_results_num": 1000000,
        "day_trend": -9381385,
        "week_trend": -18211943,
        "month_trend": 1453100
    },
    {
        "artist": "王源",
        "videos": [
            {
                "video_id": "qSVlnlblMx8",
                "title": "我们的时光",
                "upload_date": "2018-01-15T13:46:19Z",
                "views": 2331416,
                "comments": 1260,
                "likes": 26380,
                "duration": "PT3M51S"
            },
            {
                "video_id": "iafhSaA8yAs",
                "title": "我很快乐",
                "upload_date": "2025-06-06T14:01:12Z",
                "views": 1825195,
                "comments": 133,
                "likes": 4490,
                "duration": "PT3M28S"
            },
            {
                "video_id": "3D79c8ABKb8",
                "title": "下一个天亮",
                "upload_date": "2025-04-18T14:01:57Z",
                "views": 1397938,
                "comments": 280,
                "likes": 5765,
                "duration": "PT4M31S"
            },
            {
                "video_id": "aIgjPPFH6dw",
                "title": "岁月如歌",
                "upload_date": "2022-05-29T10:28:33Z",
                "views": 1374474,
                "comments": 472,
                "likes": 4895,
                "duration": "PT4M18S"
            },
            {
                "video_id": "-tbKcz12n5Q",
                "title": "十七",
                "upload_date": "2018-01-25T13:00:01Z",
                "views": 919168,
                "comments": 1146,
                "likes": 19042,
                "duration": "PT5M37S"
            },
            {
                "video_id": "f8Kz1rc7UKE",
                "title": "因为遇见你",
                "upload_date": "2016-01-13T02:49:26Z",
                "views": 758268,
                "comments": 591,
                "likes": 7962,
                "duration": "PT4M25S"
            },
            {
                "video_id": "zbjQloYGGXE",
                "title": "岁月神偷",
                "upload_date": "2025-06-20T14:27:26Z",
                "views": 669885,
                "comments": 28,
                "likes": 1214,
                "duration": "PT4M5S"
            },
            {
                "video_id": "0A4nOhiERso",
                "title": "老男孩",
                "upload_date": "2025-05-02T14:03:07Z",
                "views": 569463,
                "comments": 137,
                "likes": 2854,
                "duration": "PT5M12S"
            },
            {
                "video_id": "o-2pXXtwM5E",
                "title": "我很快乐",
                "upload_date": "2025-06-07T12:20:04Z",
                "views": 555909,
                "comments": 0,
                "likes": 1486,
                "duration": "PT3M29S"
            },
            {
                "video_id": "W6qaXHJpmUY",
                "title": "遇见",
                "upload_date": "2025-04-25T14:00:47Z",
                "views": 538063,
                "comments": 156,
                "likes": 2738,
                "duration": "PT4M3S"
            }
        ],
        "total_views": 10939779,
        "total_comments": 4203,
        "total_likes": 76826,
        "total_results_num": 1000000,
        "day_trend": -419495,
        "week_trend": -593625,
        "month_trend": -1075293
    },
    {
        "artist": "陈卓璇",
        "videos": [
            {
                "video_id": "PZrXiWGWeIs",
                "title": "爱笑的眼睛",
                "upload_date": "2017-10-30T16:20:35Z",
                "views": 17225552,
                "comments": 1627,
                "likes": 57955,
                "duration": "PT4M7S"
            },
            {
                "video_id": "I_haeWz-4Ag",
                "title": "Wu Ji",
                "upload_date": "2020-05-02T18:33:51Z",
                "views": 4933702,
                "comments": 2620,
                "likes": 131157,
                "duration": "PT2M16S"
            },
            {
                "video_id": "UjLtOYXa3J4",
                "title": "童话",
                "upload_date": "2023-10-15T13:02:38Z",
                "views": 4268548,
                "comments": 546,
                "likes": 18567,
                "duration": "PT5M53S"
            },
            {
                "video_id": "jJGkBC8Fghg",
                "title": "知足",
                "upload_date": "2023-03-31T04:01:55Z",
                "views": 3445024,
                "comments": 603,
                "likes": 14602,
                "duration": "PT5M16S"
            },
            {
                "video_id": "nJn0d05F19w",
                "title": "勇气",
                "upload_date": "2023-11-26T13:11:06Z",
                "views": 3130383,
                "comments": 190,
                "likes": 7980,
                "duration": "PT4M3S"
            },
            {
                "video_id": "AGgffBAPPa8",
                "title": "Follow the Light",
                "upload_date": "2021-06-24T02:30:30Z",
                "views": 2402782,
                "comments": 529,
                "likes": 31818,
                "duration": "PT2M29S"
            },
            {
                "video_id": "T2ldY7Kp7aQ",
                "title": "爱笑的眼睛",
                "upload_date": "2021-06-01T12:00:10Z",
                "views": 2376757,
                "comments": 560,
                "likes": 15625,
                "duration": "PT15M36S"
            },
            {
                "video_id": "3xY5cH0od34",
                "title": "喜欢你",
                "upload_date": "2022-06-16T07:00:01Z",
                "views": 2290303,
                "comments": 370,
                "likes": 22162,
                "duration": "PT10M37S"
            },
            {
                "video_id": "3zCkcN6n3KE",
                "title": "心愿便利贴",
                "upload_date": "2023-03-21T07:30:01Z",
                "views": 2082161,
                "comments": 114,
                "likes": 8444,
                "duration": "PT2M54S"
            },
            {
                "video_id": "Clg6EOKQslU",
                "title": "连名带姓",
                "upload_date": "2021-03-01T08:20:32Z",
                "views": 1900705,
                "comments": 265,
                "likes": 7785,
                "duration": "PT5M3S"
            }
        ],
        "total_views": 44055917,
        "total_comments": 7424,
        "total_likes": 316095,
        "total_results_num": 190668,
        "day_trend": -763972,
        "week_trend": -1784015,
        "month_trend": 4863885
    },
    {
        "artist": "王赫野",
        "videos": [
            {
                "video_id": "ULYksmjBwzY",
                "title": "最后一页",
                "upload_date": "2024-04-26T13:59:34Z",
                "views": 41679980,
                "comments": 1450,
                "likes": 85179,
                "duration": "PT4M35S"
            },
            {
                "video_id": "lnXn6sblxB8",
                "title": "字字句句",
                "upload_date": "2023-05-12T15:28:07Z",
                "views": 36938901,
                "comments": 1416,
                "likes": 81751,
                "duration": "PT4M58S"
            },
            {
                "video_id": "1i3EBSxjLAY",
                "title": "别让爱凋落",
                "upload_date": "2025-05-16T14:30:01Z",
                "views": 16251385,
                "comments": 6323,
                "likes": 214347,
                "duration": "PT3M35S"
            },
            {
                "video_id": "nqDTWlZKGug",
                "title": "大风吹",
                "upload_date": "2021-05-10T03:46:18Z",
                "views": 12664608,
                "comments": 919,
                "likes": 33666,
                "duration": "PT3M50S"
            },
            {
                "video_id": "o7odoNUUENE",
                "title": "是你",
                "upload_date": "2023-05-26T15:47:28Z",
                "views": 12029977,
                "comments": 410,
                "likes": 27620,
                "duration": "PT4M3S"
            },
            {
                "video_id": "FW_6AVvtHFQ",
                "title": "虹之间",
                "upload_date": "2024-05-17T14:20:28Z",
                "views": 10561024,
                "comments": 244,
                "likes": 17460,
                "duration": "PT3M24S"
            },
            {
                "video_id": "EJmwyyxP7UQ",
                "title": "何物",
                "upload_date": "2024-06-21T14:15:02Z",
                "views": 9412184,
                "comments": 366,
                "likes": 20185,
                "duration": "PT4M32S"
            },
            {
                "video_id": "3NJ1PvWXB6E",
                "title": "最后一页",
                "upload_date": "2024-07-12T11:32:02Z",
                "views": 8181992,
                "comments": 0,
                "likes": 14356,
                "duration": "PT4M41S"
            },
            {
                "video_id": "Yv6ZqpssIAk",
                "title": "晚风心里吹",
                "upload_date": "2022-04-24T05:30:09Z",
                "views": 7402098,
                "comments": 481,
                "likes": 14848,
                "duration": "PT3M39S"
            },
            {
                "video_id": "5Ue04luWaSU",
                "title": "消散对白",
                "upload_date": "2025-05-09T14:15:00Z",
                "views": 7312487,
                "comments": 283,
                "likes": 23161,
                "duration": "PT3M49S"
            }
        ],
        "total_views": 162434636,
        "total_comments": 11892,
        "total_likes": 532573,
        "total_results_num": 342289,
        "day_trend": 1722795,
        "week_trend": 2816242,
        "month_trend": 77338363
    },
    {
        "artist": "黄霄雲",
        "videos": [
            {
                "video_id": "O2q59LClA7Q",
                "title": "Sad Sometimes",
                "upload_date": "2019-09-18T17:00:04Z",
                "views": 29881756,
                "comments": 3830,
                "likes": 317477,
                "duration": "PT3M20S"
            },
            {
                "video_id": "6tk9jlKo8y4",
                "title": "星辰大海",
                "upload_date": "2021-01-28T11:11:15Z",
                "views": 28425776,
                "comments": 1729,
                "likes": 108877,
                "duration": "PT3M28S"
            },
            {
                "video_id": "VoSVmrwlvMU",
                "title": "左手指月",
                "upload_date": "2018-12-24T05:40:31Z",
                "views": 24332511,
                "comments": 5146,
                "likes": 154047,
                "duration": "PT3M"
            },
            {
                "video_id": "TLrRtCaDoOY",
                "title": "還可以愛嗎",
                "upload_date": "2018-09-24T11:10:07Z",
                "views": 13684662,
                "comments": 899,
                "likes": 47124,
                "duration": "PT4M57S"
            },
            {
                "video_id": "4Sf9aAoLqdc",
                "title": "Sad Sometimes",
                "upload_date": "2020-07-08T10:15:00Z",
                "views": 13652288,
                "comments": 994,
                "likes": 73608,
                "duration": "PT3M23S"
            },
            {
                "video_id": "7RLbRZHv1As",
                "title": "左手指月",
                "upload_date": "2018-12-21T15:00:04Z",
                "views": 12500146,
                "comments": 3487,
                "likes": 91891,
                "duration": "PT2M26S"
            },
            {
                "video_id": "S-leGr8RuL0",
                "title": "我们的爱",
                "upload_date": "2020-04-24T12:00:21Z",
                "views": 10693382,
                "comments": 2099,
                "likes": 45750,
                "duration": "PT5M23S"
            },
            {
                "video_id": "cuHLiGO2akU",
                "title": "天下无双",
                "upload_date": "2019-01-02T07:53:21Z",
                "views": 10602842,
                "comments": 3012,
                "likes": 64118,
                "duration": "PT4M32S"
            },
            {
                "video_id": "_G9ams4WTUM",
                "title": "你的答案",
                "upload_date": "2020-03-25T12:00:13Z",
                "views": 9876250,
                "comments": 1893,
                "likes": 44478,
                "duration": "PT5M7S"
            },
            {
                "video_id": "o66lL1BHOUA",
                "title": "Tay trái chỉ trăng",
                "upload_date": "2020-02-16T14:05:07Z",
                "views": 9841811,
                "comments": 1668,
                "likes": 47525,
                "duration": "PT2M58S"
            }
        ],
        "total_views": 163491424,
        "total_comments": 24757,
        "total_likes": 994895,
        "total_results_num": 410958,
        "day_trend": 261613,
        "week_trend": 421854,
        "month_trend": 1125092
    },
    {
        "artist": "伯远",
        "videos": [
            {
                "video_id": "JcjYZ6xjYtI",
                "title": "热爱105°C 的你",
                "upload_date": "2023-05-19T15:05:04Z",
                "views": 2034297,
                "comments": 387,
                "likes": 10523,
                "duration": "PT4M26S"
            },
            {
                "video_id": "07nb3dpddTY",
                "title": "若月亮没来",
                "upload_date": "2024-08-08T13:28:37Z",
                "views": 1242789,
                "comments": 186,
                "likes": 7965,
                "duration": "PT2M52S"
            },
            {
                "video_id": "gDE9IZLnigI",
                "title": "往事随风",
                "upload_date": "2023-06-02T15:07:11Z",
                "views": 627534,
                "comments": 154,
                "likes": 3236,
                "duration": "PT5M47S"
            },
            {
                "video_id": "uRpI-BIgL2g",
                "title": "破茧",
                "upload_date": "2023-09-16T05:45:02Z",
                "views": 369995,
                "comments": 200,
                "likes": 1682,
                "duration": "PT5M28S"
            },
            {
                "video_id": "Yj05mEG10YI",
                "title": "Yuan Bo",
                "upload_date": "2023-08-22T20:38:23Z",
                "views": 187096,
                "comments": 230,
                "likes": 6948,
                "duration": "PT10M11S"
            },
            {
                "video_id": "Pi8I_y7y4Y4",
                "title": "Burning Youth",
                "upload_date": "2021-06-06T04:08:38Z",
                "views": 165554,
                "comments": 129,
                "likes": 2172,
                "duration": "PT2M45S"
            },
            {
                "video_id": "1bhhB2kI43A",
                "title": "我要你的爱",
                "upload_date": "2023-10-13T05:45:11Z",
                "views": 132676,
                "comments": 142,
                "likes": 863,
                "duration": "PT3M42S"
            },
            {
                "video_id": "eWslaMH22Sc",
                "title": "If the Advisor was honest to Yuan Bo",
                "upload_date": "2024-11-06T14:00:42Z",
                "views": 45007,
                "comments": 201,
                "likes": 2777,
                "duration": "PT4M27S"
            },
            {
                "video_id": "icCQQbWbnIs",
                "title": "Have To Love",
                "upload_date": "2025-08-17T16:34:59Z",
                "views": 40003,
                "comments": 10,
                "likes": 318,
                "duration": "PT3M44S"
            },
            {
                "video_id": "NHMyKvdevM8",
                "title": "就让这大雨全都落下",
                "upload_date": "2025-08-31T13:06:15Z",
                "views": 31697,
                "comments": 13,
                "likes": 306,
                "duration": "PT4M"
            }
        ],
        "total_views": 4876648,
        "total_comments": 1652,
        "total_likes": 36790,
        "total_results_num": 300029,
        "day_trend": -5271,
        "week_trend": 10307,
        "month_trend": -233214
    },
    {
        "artist": "徐子未",
        "videos": [
            {
                "video_id": "RrJpWw19LjQ",
                "title": "慢冷",
                "upload_date": "2021-03-19T13:56:30Z",
                "views": 7799120,
                "comments": 153,
                "likes": 25688,
                "duration": "PT3M12S"
            },
            {
                "video_id": "KD6MG3YXPDo",
                "title": "慢冷",
                "upload_date": "2021-02-25T14:00:33Z",
                "views": 7636626,
                "comments": 1678,
                "likes": 43277,
                "duration": "PT3M16S"
            },
            {
                "video_id": "EkxJTjYGD70",
                "title": "情结",
                "upload_date": "2025-05-30T14:00:17Z",
                "views": 2826550,
                "comments": 122,
                "likes": 7594,
                "duration": "PT3M38S"
            },
            {
                "video_id": "_mz9KHcVolo",
                "title": "模仿",
                "upload_date": "2021-10-13T02:00:38Z",
                "views": 2314505,
                "comments": 264,
                "likes": 14566,
                "duration": "PT3M42S"
            },
            {
                "video_id": "p0uNxkSkoIs",
                "title": "燕尾蝶",
                "upload_date": "2021-03-04T11:54:25Z",
                "views": 1255450,
                "comments": 434,
                "likes": 8086,
                "duration": "PT4M25S"
            },
            {
                "video_id": "XwsSXX0kq5M",
                "title": "Slow To Cool Down",
                "upload_date": "2021-02-25T13:57:57Z",
                "views": 868961,
                "comments": 521,
                "likes": 14178,
                "duration": "PT3M35S"
            },
            {
                "video_id": "OLliqu9DmJo",
                "title": "成人",
                "upload_date": "2023-08-13T10:00:18Z",
                "views": 840335,
                "comments": 188,
                "likes": 5765,
                "duration": "PT4M27S"
            },
            {
                "video_id": "kNZTMPdCeBo",
                "title": "成双",
                "upload_date": "2024-09-03T11:30:33Z",
                "views": 624884,
                "comments": 203,
                "likes": 3808,
                "duration": "PT3M50S"
            },
            {
                "video_id": "gmlDyGxQ2Q8",
                "title": "八分钟",
                "upload_date": "2023-09-24T10:00:24Z",
                "views": 568570,
                "comments": 234,
                "likes": 4663,
                "duration": "PT8M48S"
            },
            {
                "video_id": "eqyxeM6AMoM",
                "title": "慢冷",
                "upload_date": "2021-02-26T03:12:51Z",
                "views": 379858,
                "comments": 64,
                "likes": 2398,
                "duration": "PT3M27S"
            }
        ],
        "total_views": 25114859,
        "total_comments": 3861,
        "total_likes": 130023,
        "total_results_num": 82702,
        "day_trend": 79731,
        "week_trend": 125901,
        "month_trend": 299218
    }
]